README.rst
setup.py
TestUpperCase/__init__.py
TestUpperCase.egg-info/PKG-INFO
TestUpperCase.egg-info/SOURCES.txt
TestUpperCase.egg-info/dependency_links.txt
TestUpperCase.egg-info/top_level.txt